clustering/__init__.py
clustering/dbscan.py
clustering/kmeans.py
clustering/utils.py
clustering_project-0.0.1.dist-info/METADATA
clustering_project-0.0.1.dist-info/WHEEL
clustering_project-0.0.1.dist-info/top_level.txt
clustering_project-0.0.1.dist-info/RECORD
